syntax_sugar/__init__.py
syntax_sugar/composable.py
syntax_sugar/infix.py
syntax_sugar/iter.py
syntax_sugar/match.py
syntax_sugar/pipe.py
syntax_sugar/placeholder.py
syntax_sugar/stream.py
syntax_sugar/util.py
syntax_sugar-0.3.1.dist-info/METADATA
syntax_sugar-0.3.1.dist-info/WHEEL
syntax_sugar-0.3.1.dist-info/top_level.txt
syntax_sugar-0.3.1.dist-info/RECORD
